README.txt
setup.py
funniest_sm/__init__.py
funniest_sm.egg-info/PKG-INFO
funniest_sm.egg-info/SOURCES.txt
funniest_sm.egg-info/dependency_links.txt
funniest_sm.egg-info/not-zip-safe
funniest_sm.egg-info/top_level.txt