Metadata-Version: 1.0
Name: funniest-sm
Version: 0.1
Summary: Adaptation from the funniest package tutorial
Home-page: http://blabla.bla/bla
Author: SM
Author-email: shyjee@hotmail.com
License: LN
Platform: UNKNOWN
